README.rst
setup.py
src/ctxcli.egg-info/PKG-INFO
src/ctxcli.egg-info/SOURCES.txt
src/ctxcli.egg-info/dependency_links.txt
src/ctxcli.egg-info/entry_points.txt
src/ctxcli.egg-info/requires.txt
src/ctxcli.egg-info/top_level.txt
src/cxcli/__init__.py
src/cxcli/cli.py
src/cxcli/users.py
src/cxcli/authentication/__init__.py
src/cxcli/authentication/auth.py
src/cxcli/billing/__init__.py
src/cxcli/billing/bill.py
src/cxcli/business_units/__init__.py
src/cxcli/business_units/add_users.py
src/cxcli/business_units/create_business_units.py
src/cxcli/business_units/list_business_units.py
src/cxcli/customers/__init__.py
src/cxcli/customers/customer_data.py
src/cxcli/customers/delete_customers.py
src/cxcli/migration/__init__.py
src/cxcli/migration/migration_files_cmd.py
src/cxcli/migration/migration_records_cmd.py
src/cxcli/orders/__init__.py
src/cxcli/orders/export_orders.py
src/cxcli/tenant/__init__.py
src/cxcli/tenant/list_tenants.py
src/cxcli/tools/__init__.py
src/cxcli/tools/common_utils.py
src/cxcli/tools/date_utils.py
src/cxcli/tools/excel_utils.py
src/cxcli/tools/io_utils.py
src/cxcli/tools/api_utils/__init__.py
src/cxcli/tools/api_utils/cx_caller.py
src/cxcli/tools/api_utils/cx_token.py
src/cxcli/users/__init__.py
src/cxcli/users/list_users.py