Metadata-Version: 2.1
Name: ctxcli
Version: 0.1.9
Summary: CLI Tools for Amdocs ConnectX
Author: Amdocs ConnectX
Author-email: roey@benamotz.com
License: UNKNOWN
Platform: UNKNOWN
